{
    "figname": "results/NonLinearDampedOscillator_k5/images/NLDO__PR__worst__final",
    "resfile": "results/NonLinearDampedOscillator_k5/main_bmw/NonLinearDampedOscillator_k5_PR_20230503-141425_0.res.json",
    "exp_name": "NLDO",
    "method_name": "PR",
    "name_flag": "worst",
    "iter": 262,
    "x": [0.0, 0.0, 1.0, 1.0, 1.0, 0.0, 1.0, 0.0, 1.0, 1.0, 0.0, 1.0, 1.0, 0.0, 0.0, 1.0, 1.0, 0.0, 1.0, 0.0, 0.0, 0.0, 0.0, 1.0, 1.0, 0.0, 0.0, 1.0, 1.0, 0.0, 0.0, 0.0, 1.0, 1.0, 0.0, 1.0, 0.0, 0.0, 1.0, 0.0, 0.0, 1.0],
    "y": [-0.6150075885465032],
    "c": [-0.22509869528932414]
}